SurakshaMitra/__init__.py
SurakshaMitra/email_validator.py
SurakshaMitra/file_upload_validator.py
SurakshaMitra/password_generator.py
SurakshaMitra/password_strength.py
SurakshaMitra/phone_validator.py
SurakshaMitra-2.2.0.dist-info/LICENSE
SurakshaMitra-2.2.0.dist-info/METADATA
SurakshaMitra-2.2.0.dist-info/WHEEL
SurakshaMitra-2.2.0.dist-info/top_level.txt
SurakshaMitra-2.2.0.dist-info/RECORD
