Metadata-Version: 2.2
Name: SurakshaMitra
Version: 2.2.0
Summary: A Python package for validating emails, phone numbers, password strength checking, strong password generation, and file validation.
Home-page: https://github.com/kashyapprajapat/SurakshaMitra
Author: Kashyap Prajapati
Author-email: prajapatikashyap14@gmail.com
Classifier: Development Status :: 4 - Beta
Classifier: Intended Audience :: Developers
Classifier: License :: OSI Approved :: MIT License
Classifier: Programming Language :: Python :: 3
Classifier: Programming Language :: Python :: 3.6
Classifier: Programming Language :: Python :: 3.7
Classifier: Programming Language :: Python :: 3.8
Classifier: Programming Language :: Python :: 3.9
Classifier: Programming Language :: Python :: 3.10
Classifier: Operating System :: OS Independent
Classifier: Topic :: Security
Requires-Python: >=3.6
License-File: LICENSE
Requires-Dist: phonenumbers
Dynamic: author
Dynamic: author-email
Dynamic: classifier
Dynamic: description
Dynamic: description-content-type
Dynamic: home-page
Dynamic: requires-dist
Dynamic: requires-python
Dynamic: summary
